friend/__init__.py
friend/collections.py
friend/net.py
friend/strings.py
friend/utils.py
friend-0.2.1.dist-info/DESCRIPTION.rst
friend-0.2.1.dist-info/METADATA
friend-0.2.1.dist-info/RECORD
friend-0.2.1.dist-info/WHEEL
friend-0.2.1.dist-info/metadata.json
friend-0.2.1.dist-info/top_level.txt
