Metadata-Version: 2.0
Name: friend
Version: 0.2.1
Summary: Python utility library
Home-page: https://github.com/cloudboss/friend
Author: Joseph Wright
Author-email: joseph@cloudboss.co
License: UNKNOWN
Download-URL: https://pypi.python.org/pypi/friend
Platform: UNKNOWN
